performancetest/__init__.py
performancetest/core/__init__.py
performancetest/core/command.py
performancetest/core/cpu.py
performancetest/core/device.py
performancetest/core/devicebattery.py
performancetest/core/fps.py
performancetest/core/global_data.py
performancetest/core/gpu.py
performancetest/core/iosperf.py
performancetest/core/memory.py
performancetest/core/network.py
performancetest/core/snapshot.py
performancetest/core/task_handle.py
performancetest/core/base/__init__.py
performancetest/core/base/actuator.py
performancetest/core/base/monitor.py
performancetest/test/__init__.py
performancetest/test/all_property_test.py
performancetest/web/__init__.py
performancetest/web/dao.py
performancetest/web/entity.py
performancetest/web/main.py
performancetest/web/util.py
performancetest/web/test_result/index.html
performancetest/web/test_result/iphone.png
performancetest-0.0.24.dist-info/LICENSE
performancetest-0.0.24.dist-info/METADATA
performancetest-0.0.24.dist-info/WHEEL
performancetest-0.0.24.dist-info/top_level.txt
performancetest-0.0.24.dist-info/RECORD
