Metadata-Version: 2.1
Name: performancetest
Version: 0.0.24
Summary: Android, IOS app_performance
Home-page: https://github.com/1033866383/perf-orange-cat
Author: bozhou.fan
Author-email: 15525730080@163.com
Classifier: Development Status :: 3 - Alpha
Classifier: Intended Audience :: Developers
Classifier: License :: OSI Approved :: MIT License
Classifier: Programming Language :: Python :: 3
Classifier: Programming Language :: Python :: 3.9
License-File: LICENSE
Requires-Dist: psutil ==5.9.5
Requires-Dist: airtest ==1.3.0.1
Requires-Dist: fastapi ==0.103.1
Requires-Dist: tidevice ==0.11.1
Requires-Dist: func-timeout ==4.3.5
Requires-Dist: sqlalchemy ==2.0.20
Requires-Dist: sqlalchemy-serializer ==1.4.1
Requires-Dist: uvicorn ==0.23.2
